Metadata-Version: 2.1
Name: simplerepresentations
Version: 0.0.1
Summary: Easy-to-use text representations extraction library based on the Transformers library.
Home-page: https://github.com/AliOsm/simplerepresentations
Author: Ali Fadel
Author-email: aliosm1997@gmail.com
License: Apache
Platform: UNKNOWN
Classifier: Intended Audience :: Science/Research
Classifier: License :: OSI Approved :: Apache Software License
Classifier: Programming Language :: Python :: 3
Classifier: Topic :: Scientific/Engineering :: Artificial Intelligence
Requires-Python: >=3.6
